Metadata-Version: 1.1
Name: projecttemplate
Version: 0.1.0
Summary: A template utility for data-science projects using Python that provides a skeletal project. http://projecttemplate.net
Home-page: https://github.com/Hugovdberg/projecttemplate_python
Author: Hugo van den Berg
Author-email: hugo@tbdwebdesign.nl
License: GNU General Public License v3
Keywords: projecttemplate_python
Platform: UNKNOWN
Classifier: Development Status :: 2 - Pre-Alpha
Classifier: Intended Audience :: Developers
Classifier: License :: OSI Approved :: GNU General Public License v3 (GPLv3)
Classifier: Natural Language :: English
Classifier: Programming Language :: Python :: 3
Classifier: Programming Language :: Python :: 3.5
Classifier: Programming Language :: Python :: 3.6
Classifier: Programming Language :: Python :: 3.7
Classifier: Programming Language :: Python :: 3.8
